[
{"title": ["\u9996\u9875"], "link": ["https://www.biqupa.com/"], "desc": []},
{"title": ["\u7384\u5e7b\u5947\u5e7b"], "link": ["https://www.biqupa.com/xuanhuan/"], "desc": []},
{"title": ["\u6b66\u4fa0\u4ed9\u4fa0"], "link": ["https://www.biqupa.com/xiuzhen/"], "desc": []},
{"title": ["\u90fd\u5e02\u804c\u573a"], "link": ["https://www.biqupa.com/dushi/"], "desc": []},
{"title": ["\u519b\u4e8b\u5386\u53f2"], "link": ["https://www.biqupa.com/lishi/"], "desc": []},
{"title": ["\u6e38\u620f\u4f53\u80b2"], "link": ["https://www.biqupa.com/wangyou/"], "desc": []},
{"title": ["\u79d1\u5e7b\u7075\u5f02"], "link": ["https://www.biqupa.com/kehuan/"], "desc": []},
{"title": ["\u5973\u751f\u9891\u9053"], "link": ["https://www.biqupa.com/nvsheng/"], "desc": []},
{"title": ["\u5176\u4ed6\u5c0f\u8bf4"], "link": ["https://www.biqupa.com/qita/"], "desc": []},
{"title": ["\u6392\u884c\u699c"], "link": ["https://www.biqupa.com/paihangbang/"], "desc": []},
{"title": ["\u5168\u672c\u5c0f\u8bf4"], "link": ["https://www.biqupa.com/quanben/"], "desc": []},
{"title": ["\u4e34\u65f6\u4e66\u67b6"], "link": ["https://www.biqupa.com/bookcase.html"], "desc": []}
]